ezmsg/blackrock/__init__.py
ezmsg/blackrock/__version__.py
ezmsg/blackrock/nsp.py
ezmsg/blackrock/util.py
ezmsg_blackrock-0.3.0.dist-info/METADATA
ezmsg_blackrock-0.3.0.dist-info/WHEEL
ezmsg_blackrock-0.3.0.dist-info/licenses/LICENSE.txt
ezmsg_blackrock-0.3.0.dist-info/RECORD
