Metadata-Version: 2.4
Name: ezmsg-blackrock
Version: 0.3.0
Summary: Blackrock Cerebus ecosystem interface for ezmsg
Author-email: Griffin Milsap <chadwick.boulay@gmail.com>, Chadwick Boulay <chadwick.boulay@gmail.com>
License-File: LICENSE.txt
Requires-Python: >=3.10
Requires-Dist: ezmsg-event
Requires-Dist: ezmsg>=3.6.1
Requires-Dist: pycbsdk>=0.4.0
